dwave_ocean_sdk-9.2.0.dist-info/licenses/LICENSE
dwaveoceansdk/__init__.py
dwaveoceansdk/package_info.py
dwave_ocean_sdk-9.2.0.dist-info/METADATA
dwave_ocean_sdk-9.2.0.dist-info/WHEEL
dwave_ocean_sdk-9.2.0.dist-info/top_level.txt
dwave_ocean_sdk-9.2.0.dist-info/RECORD
