Metadata-Version: 2.4
Name: dwave-ocean-sdk
Version: 9.2.0
Summary: Software development kit for open source D-Wave tools
Home-page: https://github.com/dwavesystems/dwave-ocean-sdk
Author: D-Wave
Author-email: tools@dwavesys.com
License: Apache 2.0
Project-URL: Changes, https://github.com/dwavesystems/dwave-ocean-sdk/releases
Project-URL: Documentation, https://docs.dwavequantum.com/
Project-URL: Source Code, https://github.com/dwavesystems/dwave-ocean-sdk
Classifier: License :: OSI Approved :: Apache Software License
Classifier: Operating System :: OS Independent
Classifier: Programming Language :: Python :: 3 :: Only
Classifier: Programming Language :: Python :: 3.10
Classifier: Programming Language :: Python :: 3.11
Classifier: Programming Language :: Python :: 3.12
Classifier: Programming Language :: Python :: 3.13
Classifier: Programming Language :: Python :: 3.14
Requires-Python: >=3.10
License-File: LICENSE
Requires-Dist: dimod==0.12.21
Requires-Dist: dwave-cloud-client==0.14.3
Requires-Dist: dwave-gate==0.3.5
Requires-Dist: dwave-hybrid==0.6.14
Requires-Dist: dwave-inspector==0.5.5
Requires-Dist: dwave-networkx==0.8.18
Requires-Dist: dwave-optimization==0.6.9
Requires-Dist: dwave-preprocessing==0.6.11
Requires-Dist: dwave-samplers==1.7.0
Requires-Dist: dwave-system==1.34.0
Requires-Dist: minorminer==0.2.21
Requires-Dist: penaltymodel==1.3.0
Provides-Extra: all
Dynamic: license-file
